rupy/__init__.py
rupy/rupy.cpython-313-darwin.so
rupy_api-0.2.0.dist-info/METADATA
rupy_api-0.2.0.dist-info/WHEEL
rupy_api-0.2.0.dist-info/licenses/LICENSE
rupy_api-0.2.0.dist-info/RECORD
