Metadata-Version: 2.4
Name: rupy-api
Version: 0.2.0
Classifier: Programming Language :: Rust
Classifier: Programming Language :: Python :: Implementation :: CPython
Classifier: Programming Language :: Python :: 3
Requires-Dist: requests>=2.25.0 ; extra == 'dev'
Provides-Extra: dev
License-File: LICENSE
Summary: A high-performance web framework for Python, powered by Rust and Axum
Author: Manoel Carvalho
License: MIT
Requires-Python: >=3.8
